shoppyapi/__init__.py
shoppyapi/shoppyapi.py
shoppyapi/version.py
shoppyapi-1.0.0.dist-info/METADATA
shoppyapi-1.0.0.dist-info/WHEEL
shoppyapi-1.0.0.dist-info/top_level.txt
shoppyapi-1.0.0.dist-info/RECORD
